pacote_pypi_01/__init__.py
pacote_pypi_01/circulo.py
pacote_pypi_01/figura_geometrica.py
pacote_pypi_01/quadrado.py
pacote_pypi_robson-0.1.4.data/data/pacote_pypi_01/dados.json
test/__init__.py
test/circulo_test.py
test/figura_geometrica_test.py
test/quadrado_test.py
pacote_pypi_robson-0.1.4.dist-info/METADATA
pacote_pypi_robson-0.1.4.dist-info/WHEEL
pacote_pypi_robson-0.1.4.dist-info/top_level.txt
pacote_pypi_robson-0.1.4.dist-info/RECORD
