Metadata-Version: 2.1
Name: pacote-pypi-robson
Version: 0.1.4
Summary: Descrição rapida do que e esse pacote
Home-page: https://github.com/mstuttgart/codigo-avulso-test-tutorial
Author: Francisco Robson
Author-email: email@gmail.com
License: UNKNOWN
Keywords: tutorial pip pacotes robson
Platform: UNKNOWN
Classifier: Programming Language :: Python :: 3
Classifier: License :: OSI Approved :: MIT License
Classifier: Operating System :: OS Independent
